typing_inspection/__init__.py
typing_inspection/introspection.py
typing_inspection/py.typed
typing_inspection/typing_objects.py
typing_inspection/typing_objects.pyi
typing_inspection-0.3.1.dist-info/METADATA
typing_inspection-0.3.1.dist-info/WHEEL
typing_inspection-0.3.1.dist-info/licenses/LICENSE
typing_inspection-0.3.1.dist-info/RECORD
